max_logger/color.py
max_logger/main.py
max_logger-1.0.0.dist-info/entry_points.txt
max_logger-1.0.0.dist-info/LICENSE
max_logger-1.0.0.dist-info/WHEEL
max_logger-1.0.0.dist-info/METADATA
max_logger-1.0.0.dist-info/RECORD
