Metadata-Version: 2.1
Name: max-logger
Version: 1.0.0
Summary: Max's custom loguru sinks, logger helper functions, rich tracebacks and other helper functions for rich.
License: MIT
Author: Max Ludden
Author-email: dev@maxludden.com
Requires-Python: >=3.10,<4.0
Classifier: License :: OSI Approved :: MIT License
Classifier: Programming Language :: Python :: 3
Classifier: Programming Language :: Python :: 3.10
Classifier: Programming Language :: Python :: 3.11
Requires-Dist: loguru (>=0.6.0,<0.7.0)
Requires-Dist: rich[all] (>=12.6.0,<13.0.0)
Requires-Dist: ujson (>=5.5.0,<6.0.0)
